fast_tx/__init__.py
fast_tx/buffer_tools.py
fast_tx/core.py
fast_tx/experimental.py
fast_tx/stk_tools.py
fast_tx/stk_tx.py
fast_tx/utils.py
fast_tx-0.1.1.dist-info/METADATA
fast_tx-0.1.1.dist-info/WHEEL
fast_tx-0.1.1.dist-info/licenses/LICENSE
fast_tx-0.1.1.dist-info/RECORD
