Metadata-Version: 2.4
Name: fast-tx
Version: 0.1.1
Summary: Fast row and column transformations for pandas.
Project-URL: Homepage, https://github.com/aocks/fast_tx
Project-URL: Repository, https://github.com/aocks/fast_tx
Project-URL: Issues, https://github.com/aocks/fast_tx/issues
Author-email: Emin Martinian <emin@aocks.com>
License: MIT License
License-File: LICENSE
Keywords: dataframe,numba,pandas,performance,transformation
Classifier: Development Status :: 3 - Alpha
Classifier: Intended Audience :: Developers
Classifier: License :: OSI Approved :: MIT License
Classifier: Programming Language :: Python :: 3
Classifier: Programming Language :: Python :: 3.11
Classifier: Programming Language :: Python :: 3.12
Classifier: Topic :: Software Development :: Libraries :: Python Modules
Requires-Python: >=3.11
Requires-Dist: numba>=0.57.0
Requires-Dist: numpy>=2.0.0
Requires-Dist: pandas>=2.0.0
